opentracing_decorator/__init__.py
opentracing_decorator/__version__.py
opentracing_decorator/py.typed
opentracing_decorator/tracing.py
opentracing_decorator-1.1.0.dist-info/LICENSE
opentracing_decorator-1.1.0.dist-info/METADATA
opentracing_decorator-1.1.0.dist-info/WHEEL
opentracing_decorator-1.1.0.dist-info/top_level.txt
opentracing_decorator-1.1.0.dist-info/RECORD
