Metadata-Version: 2.1
Name: opentracing-decorator
Version: 1.1.0
Summary: A Python decorator for OpenTracing trace generation.
Home-page: https://github.com/doughepi/opentracing-decorator
Author: Piper Dougherty
Author-email: doughertypiper@gmail.com
License: MIT
Project-URL: Documentation, https://doughepi.github.io/opentracing-decorator/
Project-URL: Source, https://github.com/doughepi/opentracing-decorator
Keywords: tracing,opentracing,decorator
Platform: UNKNOWN
Classifier: Development Status :: 4 - Beta
Classifier: Environment :: Web Environment
Classifier: Intended Audience :: Developers
Classifier: License :: OSI Approved :: MIT License
Classifier: Operating System :: OS Independent
Classifier: Topic :: Internet :: WWW/HTTP
Classifier: Programming Language :: Python :: 3
Classifier: Programming Language :: Python :: 3.7
Classifier: Programming Language :: Python :: 3.8
Classifier: Programming Language :: Python :: 3.9
Classifier: Programming Language :: Python :: 3 :: Only
Requires-Python: >=3.7
Requires-Dist: opentracing (<3.0,>=2.4.0)
Requires-Dist: flatten-dict (==0.3.0)
Provides-Extra: tests
